setup.py
RedeSociaisLume.egg-info/PKG-INFO
RedeSociaisLume.egg-info/SOURCES.txt
RedeSociaisLume.egg-info/dependency_links.txt
RedeSociaisLume.egg-info/requires.txt
RedeSociaisLume.egg-info/top_level.txt
redesociais/__init__.py
redesociais/api/__init__.py
redesociais/api/facebook.py
redesociais/utils/__init__.py
redesociais/utils/geradores.py