Metadata-Version: 1.0
Name: RedeSociaisLume
Version: 0.0.1
Summary: Pacote para conexão com apis de rede sociais
Home-page: https://gitlab.com/agencia-lume/rede-sociais-api
Author: Agência Lume
Author-email: ti@agencialume.com
License: UNKNOWN
Platform: UNKNOWN
